<ArrayOfShip xmlns="http://schemas.datacontract.org/2004/07/Components.Battle.Ship" xmlns:i="http://www.w3.org/2001/XMLSchema-instance"><Ship i:type="BattleShip"><ShipName>BattleShip</ShipName><_cordinates><Cordinate><x>0</x><y>0</y></Cordinate><Cordinate><x>1</x><y>0</y></Cordinate><Cordinate><x>2</x><y>0</y></Cordinate><Cordinate><x>3</x><y>0</y></Cordinate></_cordinates><_hits>0</_hits> <_shipType>Battleship</_shipType><_sizeShip>4</_sizeShip></Ship><Ship i:type="CruiserShip"><ShipName>CruiserShip</ShipName><_cordinates><Cordinate><x>0</x><y>1</y></Cordinate><Cordinate><x>1</x><y>1</y></Cordinate><Cordinate><x>2</x><y>1</y></Cordinate></_cordinates><_hits>0</_hits> <_shipType>Cruiser</_shipType><_sizeShip>3</_sizeShip></Ship><Ship i:type="DestroyerShip"><ShipName>DestroyerShip</ShipName><_cordinates><Cordinate><x>0</x><y>2</y></Cordinate><Cordinate><x>1</x><y>2</y></Cordinate></_cordinates><_hits>0</_hits> <_shipType>Destroyer</_shipType><_sizeShip>2</_sizeShip></Ship><Ship i:type="SubmarineShip"><ShipName>SubmarineShip</ShipName><_cordinates><Cordinate><x>0</x><y>3</y></Cordinate></_cordinates><_hits>0</_hits> <_shipType>Submarine</_shipType><_sizeShip>1</_sizeShip></Ship><Ship i:type="CarrierShip"><ShipName>CarrierShip</ShipName><_cordinates><Cordinate><x>0</x><y>4</y></Cordinate><Cordinate><x>1</x><y>4</y></Cordinate><Cordinate><x>2</x><y>4</y></Cordinate><Cordinate><x>3</x><y>4</y></Cordinate><Cordinate><x>4</x><y>4</y></Cordinate></_cordinates><_hits>0</_hits> <_shipType>Carrier</_shipType><_sizeShip>5</_sizeShip></Ship></ArrayOfShip>